sctm-0.1.3.dist-info/METADATA
sctm-0.1.3.dist-info/WHEEL
sctm/.vscode/settings.json
sctm/__init__.py
sctm/__pycache__/dist.cpython-39.pyc.139925693191984
sctm/__pycache__/model.cpython-39.pyc.139648853430960
sctm/__pycache__/model.cpython-39.pyc.140246342949296
sctm/analysis.py
sctm/data.py
sctm/dist.py
sctm/layers.py
sctm/metrics.py
sctm/model.py
sctm/pl.py
sctm/pp.py
sctm/rbo.py
sctm/seed.py
sctm/stamp.py
sctm/utils.py
sctm-0.1.3.dist-info/RECORD
