Metadata-Version: 2.1
Name: scTM
Version: 0.1.3
Summary: A toolbox for single cell topic models
Author-Email: chengwei94 <chengwei8@gmail.com>
License: MIT
Requires-Python: >=3.8
Requires-Dist: scanpy>=1.9.3
Requires-Dist: anndata>=0.9.1
Requires-Dist: gseapy>=1.0.4
Requires-Dist: pyro-ppl>=1.8.4
Requires-Dist: squidpy>=1.2.2
Requires-Dist: torch>=2.0.1
Requires-Dist: torchinfo>=1.8.0
Requires-Dist: discotoolkit>=1.0.0.1
Requires-Dist: scikit-misc>=0.2.0
